setup.py
lib/wc/__init__.py
lib/wc/socket/__init__.py
lib/wc_socket.egg-info/PKG-INFO
lib/wc_socket.egg-info/SOURCES.txt
lib/wc_socket.egg-info/dependency_links.txt
lib/wc_socket.egg-info/eager_resources.txt
lib/wc_socket.egg-info/namespace_packages.txt
lib/wc_socket.egg-info/not-zip-safe
lib/wc_socket.egg-info/top_level.txt