Metadata-Version: 1.0
Name: wc-socket
Version: 1.0.0
Summary: WidgetCo socket: This is a fake socket module used to teach namespace packages ( http://www.sourceweaver.com/posts/python-namespace-packages).
Home-page: UNKNOWN
Author: Oisin Mulvihill
Author-email: oisinmulvihill at gmail dot com
License: BSD License
Platform: UNKNOWN
